Metadata-Version: 2.4
Name: adafruit-circuitpython-pca9554
Version: 1.0.7
Summary: CircuitPython library for Adafruit PCA9554 GPIO expanders
Author-email: Adafruit Industries <circuitpython@adafruit.com>
License: MIT
Project-URL: Homepage, https://github.com/adafruit/Adafruit_CircuitPython_PCA9554
Keywords: adafruit,blinka,circuitpython,micropython,pca9554,PCA9554,gpio,expander
Classifier: Intended Audience :: Developers
Classifier: Topic :: Software Development :: Libraries
Classifier: Topic :: Software Development :: Embedded Systems
Classifier: Topic :: System :: Hardware
Classifier: License :: OSI Approved :: MIT License
Classifier: Programming Language :: Python :: 3
License-File: LICENSE
Requires-Dist: Adafruit-Blinka
Requires-Dist: adafruit-circuitpython-busdevice
Provides-Extra: optional
Dynamic: license-file
